code_quality_local.py
code_quality_local_python.py
code_quality_transform.py
code_quality_transform_python.py
dpk_code_quality_transform_python-0.2.0.dist-info/METADATA
dpk_code_quality_transform_python-0.2.0.dist-info/WHEEL
dpk_code_quality_transform_python-0.2.0.dist-info/top_level.txt
dpk_code_quality_transform_python-0.2.0.dist-info/RECORD
